fast_mda_traceroute/__init__.py
fast_mda_traceroute/__main__.py
fast_mda_traceroute/algorithms/__init__.py
fast_mda_traceroute/algorithms/diamond_miner.py
fast_mda_traceroute/cli.py
fast_mda_traceroute/commands/__init__.py
fast_mda_traceroute/commands/paris_traceroute.py
fast_mda_traceroute/commands/scamper.py
fast_mda_traceroute/dns.py
fast_mda_traceroute/formats/__init__.py
fast_mda_traceroute/formats/scamper.py
fast_mda_traceroute/formats/table.py
fast_mda_traceroute/formats/traceroute.py
fast_mda_traceroute/links.py
fast_mda_traceroute/logger.py
fast_mda_traceroute/typing.py
fast_mda_traceroute/utils.py
fast_mda_traceroute-0.1.13.dist-info/LICENSE
fast_mda_traceroute-0.1.13.dist-info/METADATA
fast_mda_traceroute-0.1.13.dist-info/WHEEL
fast_mda_traceroute-0.1.13.dist-info/entry_points.txt
fast_mda_traceroute-0.1.13.dist-info/RECORD
