Metadata-Version: 2.1
Name: fast-mda-traceroute
Version: 0.1.13
Summary: An experimental multipath traceroute tool.
Home-page: https://github.com/dioptra-io/fast-mda-traceroute
License: MIT
Author: Maxime Mouchet
Author-email: maxime.mouchet@lip6.fr
Requires-Python: >=3.10,<4.0
Classifier: License :: OSI Approved :: MIT License
Classifier: Programming Language :: Python :: 3
Classifier: Programming Language :: Python :: 3.10
Classifier: Programming Language :: Python :: 3.11
Requires-Dist: diamond-miner (>=1.0.3,<2.0.0)
Requires-Dist: more-itertools (>=8.12.0,<9.0.0)
Requires-Dist: pycaracal (>=0.14.5,<0.15.0)
Requires-Dist: tabulate (>=0.8.9,<0.9.0)
Requires-Dist: typer (>=0.4.0,<0.5.0)
